[{"tag":{"S":"304VbPK6Y4RGeXtW6xVfF/_N_T_/layout"},"path":{"S":"304VbPK6Y4RGeXtW6xVfF/_not-found"},"revalidatedAt":{"N":"1"}},{"tag":{"S":"304VbPK6Y4RGeXtW6xVfF/_N_T_/_not-found/layout"},"path":{"S":"304VbPK6Y4RGeXtW6xVfF/_not-found"},"revalidatedAt":{"N":"1"}},{"tag":{"S":"304VbPK6Y4RGeXtW6xVfF/_N_T_/_not-found/page"},"path":{"S":"304VbPK6Y4RGeXtW6xVfF/_not-found"},"revalidatedAt":{"N":"1"}},{"tag":{"S":"304VbPK6Y4RGeXtW6xVfF/_N_T_/_not-found"},"path":{"S":"304VbPK6Y4RGeXtW6xVfF/_not-found"},"revalidatedAt":{"N":"1"}},{"tag":{"S":"304VbPK6Y4RGeXtW6xVfF/_N_T_/layout"},"path":{"S":"304VbPK6Y4RGeXtW6xVfF/index"},"revalidatedAt":{"N":"1"}},{"tag":{"S":"304VbPK6Y4RGeXtW6xVfF/_N_T_/page"},"path":{"S":"304VbPK6Y4RGeXtW6xVfF/index"},"revalidatedAt":{"N":"1"}},{"tag":{"S":"304VbPK6Y4RGeXtW6xVfF/_N_T_/"},"path":{"S":"304VbPK6Y4RGeXtW6xVfF/index"},"revalidatedAt":{"N":"1"}},{"tag":{"S":"304VbPK6Y4RGeXtW6xVfF/_N_T_/layout"},"path":{"S":"304VbPK6Y4RGeXtW6xVfF/login"},"revalidatedAt":{"N":"1"}},{"tag":{"S":"304VbPK6Y4RGeXtW6xVfF/_N_T_/(auth)/layout"},"path":{"S":"304VbPK6Y4RGeXtW6xVfF/login"},"revalidatedAt":{"N":"1"}},{"tag":{"S":"304VbPK6Y4RGeXtW6xVfF/_N_T_/(auth)/login/layout"},"path":{"S":"304VbPK6Y4RGeXtW6xVfF/login"},"revalidatedAt":{"N":"1"}},{"tag":{"S":"304VbPK6Y4RGeXtW6xVfF/_N_T_/(auth)/login/page"},"path":{"S":"304VbPK6Y4RGeXtW6xVfF/login"},"revalidatedAt":{"N":"1"}},{"tag":{"S":"304VbPK6Y4RGeXtW6xVfF/_N_T_/login"},"path":{"S":"304VbPK6Y4RGeXtW6xVfF/login"},"revalidatedAt":{"N":"1"}},{"tag":{"S":"304VbPK6Y4RGeXtW6xVfF/_N_T_/layout"},"path":{"S":"304VbPK6Y4RGeXtW6xVfF/reset-password"},"revalidatedAt":{"N":"1"}},{"tag":{"S":"304VbPK6Y4RGeXtW6xVfF/_N_T_/(auth)/layout"},"path":{"S":"304VbPK6Y4RGeXtW6xVfF/reset-password"},"revalidatedAt":{"N":"1"}},{"tag":{"S":"304VbPK6Y4RGeXtW6xVfF/_N_T_/(auth)/reset-password/layout"},"path":{"S":"304VbPK6Y4RGeXtW6xVfF/reset-password"},"revalidatedAt":{"N":"1"}},{"tag":{"S":"304VbPK6Y4RGeXtW6xVfF/_N_T_/(auth)/reset-password/page"},"path":{"S":"304VbPK6Y4RGeXtW6xVfF/reset-password"},"revalidatedAt":{"N":"1"}},{"tag":{"S":"304VbPK6Y4RGeXtW6xVfF/_N_T_/reset-password"},"path":{"S":"304VbPK6Y4RGeXtW6xVfF/reset-password"},"revalidatedAt":{"N":"1"}},{"tag":{"S":"304VbPK6Y4RGeXtW6xVfF/_N_T_/layout"},"path":{"S":"304VbPK6Y4RGeXtW6xVfF/signup"},"revalidatedAt":{"N":"1"}},{"tag":{"S":"304VbPK6Y4RGeXtW6xVfF/_N_T_/(auth)/layout"},"path":{"S":"304VbPK6Y4RGeXtW6xVfF/signup"},"revalidatedAt":{"N":"1"}},{"tag":{"S":"304VbPK6Y4RGeXtW6xVfF/_N_T_/(auth)/signup/layout"},"path":{"S":"304VbPK6Y4RGeXtW6xVfF/signup"},"revalidatedAt":{"N":"1"}},{"tag":{"S":"304VbPK6Y4RGeXtW6xVfF/_N_T_/(auth)/signup/page"},"path":{"S":"304VbPK6Y4RGeXtW6xVfF/signup"},"revalidatedAt":{"N":"1"}},{"tag":{"S":"304VbPK6Y4RGeXtW6xVfF/_N_T_/signup"},"path":{"S":"304VbPK6Y4RGeXtW6xVfF/signup"},"revalidatedAt":{"N":"1"}}]